ratelimit-stubs/__init__.pyi
ratelimit-stubs/decorators.pyi
ratelimit_types-0.0.3.dist-info/LICENSE.txt
ratelimit_types-0.0.3.dist-info/METADATA
ratelimit_types-0.0.3.dist-info/WHEEL
ratelimit_types-0.0.3.dist-info/RECORD
