Metadata-Version: 2.3
Name: ratelimit-types
Version: 0.0.3
Summary: PEP 561 type stubs for ratelimit.
License: MIT
Keywords: pep561,stubs,types
Author: Andrew Udvare
Author-email: audvare@gmail.com
Requires-Python: >=3.10,<3.14
Classifier: Development Status :: 2 - Pre-Alpha
Classifier: Intended Audience :: Developers
Classifier: License :: OSI Approved :: MIT License
Classifier: Programming Language :: Python
Classifier: Programming Language :: Python :: 3.10
Classifier: Programming Language :: Python :: 3.11
Classifier: Programming Language :: Python :: 3.12
Classifier: Programming Language :: Python :: 3.13
Classifier: Typing :: Stubs Only
Requires-Dist: typing-extensions (>=4.13.1,<5.0.0)
Project-URL: Documentation, https://ratelimit-types.readthedocs.org
Project-URL: Homepage, https://tatsh.github.io/ratelimit-types/
Project-URL: Issues, https://github.com/Tatsh/ratelimit-types/issues
Project-URL: Repository, https://github.com/Tatsh/ratelimit-types
